{
  "kind": "collectionType",
  "collectionName": "services",
  "info": {
    "singularName": "service",
    "pluralName": "services",
    "displayName": "Services",
    "description": ""
  },
  "options": {
    "draftAndPublish": true
  },
  "pluginOptions": {
    "i18n": {
      "localized": true
    },
    "versions": {
      "versioned": true
    }
  },
  "attributes": {
    "name": {
      "type": "string",
      "required": true,
      "pluginOptions": {
        "i18n": {
          "localized": true
        }
      }
    },
    "order": {
      "type": "integer",
      "required": true,
      "unique": false,
      "min": 1
    },
    "slug": {
      "type": "string",
      "targetField": "name",
      "required": true
    },
    "description": {
      "pluginOptions": {
        "i18n": {
          "localized": true
        }
      },
      "type": "text",
      "required": true
    },
    "icon": {
      "type": "media",
      "multiple": false,
      "required": true,
      "allowedTypes": ["images"],
      "pluginOptions": {
        "i18n": {
          "localized": false
        }
      }
    }
  }
}
